tzk/__init__.py
tzk/__main__.py
tzk/builders.py
tzk/config.py
tzk/default_config.py
tzk/git.py
tzk/tw.py
tzk/util.py
tzk/editions/tzk/tiddlywiki.info
tzk/editions/tzk/plugins/3click2edit/plugin.info
tzk/editions/tzk/plugins/3click2edit/_system/plugins/danielo515/2click2edit/ClickListener.js
tzk/editions/tzk/plugins/3click2edit/_system/plugins/danielo515/2click2edit/ClickListener.js.meta
tzk/editions/tzk/plugins/3click2edit/_system/plugins/danielo515/2click2edit/readme.tid
tzk/editions/tzk/plugins/3click2edit/_system/plugins/danielo515/2click2edit/ui/ViewTemplate.tid
tzk/editions/tzk/plugins/Calendar/plugin.info
tzk/editions/tzk/plugins/Calendar/_system/config/bj/Calendar.json
tzk/editions/tzk/plugins/Calendar/_system/config/bj/Calendar.json.meta
tzk/editions/tzk/plugins/Calendar/_system/core/modules/widgets/macrorefresh.js
tzk/editions/tzk/plugins/Calendar/_system/core/modules/widgets/macrorefresh.js.meta
tzk/editions/tzk/plugins/Calendar/_system/macros/bj/Calendar/diary.js
tzk/editions/tzk/plugins/Calendar/_system/macros/bj/Calendar/diary.js.meta
tzk/editions/tzk/plugins/Calendar/_system/macros/bj/Calendar/journalfmt.js
tzk/editions/tzk/plugins/Calendar/_system/macros/bj/Calendar/journalfmt.js.meta
tzk/editions/tzk/plugins/Calendar/_system/macros/bj/Calendar/journalslinked.js
tzk/editions/tzk/plugins/Calendar/_system/macros/bj/Calendar/journalslinked.js.meta
tzk/editions/tzk/plugins/Calendar/_system/macros/buggyj/Calendar/base.js
tzk/editions/tzk/plugins/Calendar/_system/macros/buggyj/Calendar/base.js.meta
tzk/editions/tzk/plugins/Calendar/_system/macros/buggyj/Calendar/entry.js
tzk/editions/tzk/plugins/Calendar/_system/macros/buggyj/Calendar/entry.js.meta
tzk/editions/tzk/plugins/Calendar/_system/macros/buggyj/Calendar/entry2.js
tzk/editions/tzk/plugins/Calendar/_system/macros/buggyj/Calendar/entry2.js.meta
tzk/editions/tzk/plugins/Calendar/_system/macros/buggyj/Calendar/ifnew.js
tzk/editions/tzk/plugins/Calendar/_system/macros/buggyj/Calendar/ifnew.js.meta
tzk-0.5.1.dist-info/licenses/LICENSE
tzk-0.5.1.dist-info/METADATA
tzk-0.5.1.dist-info/WHEEL
tzk-0.5.1.dist-info/entry_points.txt
tzk-0.5.1.dist-info/top_level.txt
tzk-0.5.1.dist-info/RECORD
